synthetic_data_crafter/__init__.py
synthetic_data_crafter/base_generator.py
synthetic_data_crafter/core.py
synthetic_data_crafter/dataset_manager.py
synthetic_data_crafter/exporters.py
synthetic_data_crafter/provider_factory.py
synthetic_data_crafter/external_datasets/csv/ICD10_diagnosis.csv
synthetic_data_crafter/external_datasets/csv/ICD10_procedure.csv
synthetic_data_crafter/external_datasets/csv/ICD9_diagnosis.csv
synthetic_data_crafter/external_datasets/csv/ICD9_procedure.csv
synthetic_data_crafter/external_datasets/csv/airlines.csv
synthetic_data_crafter/external_datasets/csv/airport.csv
synthetic_data_crafter/external_datasets/csv/animals.csv
synthetic_data_crafter/external_datasets/csv/app.csv
synthetic_data_crafter/external_datasets/csv/athlete.csv
synthetic_data_crafter/external_datasets/csv/bank.csv
synthetic_data_crafter/external_datasets/csv/books.csv
synthetic_data_crafter/external_datasets/csv/cars.csv
synthetic_data_crafter/external_datasets/csv/colors.csv
synthetic_data_crafter/external_datasets/csv/company.csv
synthetic_data_crafter/external_datasets/csv/construction_code.csv
synthetic_data_crafter/external_datasets/csv/countries.csv
synthetic_data_crafter/external_datasets/csv/cryptocurrency.csv
synthetic_data_crafter/external_datasets/csv/css_class.csv
synthetic_data_crafter/external_datasets/csv/drugs.csv
synthetic_data_crafter/external_datasets/csv/hcpcs.csv
synthetic_data_crafter/external_datasets/csv/hospital.csv
synthetic_data_crafter/external_datasets/csv/language.csv
synthetic_data_crafter/external_datasets/csv/movies.csv
synthetic_data_crafter/external_datasets/csv/noise.csv
synthetic_data_crafter/external_datasets/csv/period_table.csv
synthetic_data_crafter/external_datasets/csv/plants.csv
synthetic_data_crafter/external_datasets/csv/product.csv
synthetic_data_crafter/external_datasets/csv/slogan.csv
synthetic_data_crafter/external_datasets/csv/states.csv
synthetic_data_crafter/external_datasets/csv/stocks.csv
synthetic_data_crafter-1.1.5.dist-info/licenses/LICENSE
synthetic_data_crafter-1.1.5.dist-info/METADATA
synthetic_data_crafter-1.1.5.dist-info/WHEEL
synthetic_data_crafter-1.1.5.dist-info/top_level.txt
synthetic_data_crafter-1.1.5.dist-info/RECORD
