Metadata-Version: 2.4
Name: synthetic-data-crafter
Version: 1.1.5
Summary: Generate hyper-realistic synthetic data at scale — 750+ field types, real-world distributions, relational schemas, and one-click export to CSV, JSON, Parquet, SQL, Excel, Avro, and more.
Home-page: https://github.com/ikigamisama/SyntheticDataCrafter
Author: Franz Monzales
Author-email: ikigamidevs@gmail.com
Classifier: Programming Language :: Python :: 3
Classifier: License :: OSI Approved :: MIT License
Classifier: Operating System :: OS Independent
Requires-Python: >=3.8
License-File: LICENSE
Requires-Dist: duckdb
Requires-Dist: lorem_text
Requires-Dist: numpy
Requires-Dist: openpyxl
Requires-Dist: pandas
Requires-Dist: pyarrow
Requires-Dist: bcrypt
Requires-Dist: python_dateutil
Requires-Dist: rstr
Dynamic: license-file
